Workbook

Sheet Read me
A1: ShopBack Lens - Impact Model
A2: Wang Zhiming (王至明) | Singapore launch | 12-month horizon | v1.1 | 29 Sep 2026
B3: How to use this model
B4: Every orange cell on the 'Assumptions' tab is an input you can change. Every other number in the workbook is a live formula that recalculates from those inputs. Nothing is hard-coded downstream.
B6: These are not forecasts
B7: I do not have access to ShopBack's internal data. The outputs here are the arithmetic consequences of the stated assumptions - no more than that. Each assumption carries a confidence rating and a named test that would confirm or kill it. The purpose of the model is to show which assumptions the business case actually hangs on, so that the first month of work can be aimed at those and nothing else.
B9: The three assumptions that matter
B10: A-1 Leakage rate - what share of purchases at partner merchants never pass through ShopBack. This sets the size of the recoverable pool and therefore whether this is a S$2M or a S$20M project.
B11: A-4 Match rate - can the catalogue reliably resolve a social link or screenshot to a product. If this fails, there is no product. It is tested offline in month zero, before any client code.
B12: A-8 Incrementality - what share of Lens orders would not have been tracked anyway. If this is low, Lens is redistributing revenue rather than creating it, and is a cost line.
B14: Tabs
B15: Assumptions All editable inputs, with confidence and validation method
B16: Lens funnel Capture-to-order funnel and incremental GMV, driven by the assumptions tab
B17: Smart Rates Platform fee (71 bps) on participating GMV. Extra cashback is a merchant pass-through.
... B19: Metrics North star, inputs, guardrails and counter-metric, with targets and owners

Sheet Assumptions
A1: Assumptions
A2: Orange cells are editable inputs. Everything else in this workbook derives from them.
A4: ID | B4: Assumption | C4: Input | D4: Unit | E4: Confidence | F4: How it gets validated / killed
A5: A-13 | B5: SG monthly active users | C5: 600000 | D5: users | E5: Unknown | F5: Internal data - I do not have it. Single editable input so the whole model rescales.
A6: A-1 | B6: Leakage: partner-merchant purchases that never pass through ShopBack | C6: 0.6 | D6: % | E6: Low | F6: Panel survey of 500 SG users + opt-in email-receipt panel. KILL below 30%.
A7: A-2 | B7: Lens monthly adoption as share of SG MAU at M12 | C7: 0.22 | D7: % | E7: Low | F7: Staged rollout with holdout; organic vs prompted discovery. KILL below 8%.
A8: A-3 | B8: Lens submissions per Lens-active user per month | C8: 3.2 | D8: count | E8: Low | F8: Direct beta measurement. KILL below 1.5 - that is novelty, not habit.
A9: A-4 | B9: Match rate: submissions resolved to a confident product match | C9: 0.78 | D9: % | E9: Medium | F9: Offline eval on 2,000 real social links/screenshots in month 0. KILL below 55%.
A10: A-6 | B10: Match to click-out rate | C10: 0.46 | D10: % | E10: Low | F10: Beta funnel. KILL below 20% - the answer is not compelling.
A11: A-7 | B11: Click-out to order conversion | C11: 0.095 | D11: % | E11: Medium | F11: Beta funnel, benchmarked against current ShopBack click-out conversion. KILL below 4%.
A12: A-8 | B12: Incrementality: Lens orders that would not otherwise be tracked | C12: 0.55 | D12: % | E12: Low | F12: 10% user-level holdout for 8 weeks. KILL below 25% - Lens is cannibalising.
A13: A-12 | B13: Average order value on Lens orders | C13: 95 | D13: SGD | E13: Medium | F13: Beta measurement against current ShopBack SG AOV.
A14: A-11 | B14: Retention lift: extra tracked orders per Lens user per month, placed OUTSIDE Lens | C14: 0.015 | D14: count | E14: Low | F14: Same holdout as A-8. Deliberately set low - this is the softest line in the model and the easiest to double-count.
A15: P-2 | B15: Net take rate retained by ShopBack after user cashback | C15: 0.024 | D15: % | E15: Medium | F15: Industry norm for affiliate cashback. Replace with actuals on day one.
A16: A-15 | B16: SG annual tracked GMV (base for Smart Rates) | C16: 400000000 | D16: SGD | E16: Unknown | F16: Internal data. Smart Rates value scales linearly with this.
... A21: A-18 | B21: MY + TW combined run-rate as a multiple of SG, at M12 exit | C21: 3.2 | D21: count | E21: Low | F21: Scaled on relative e-commerce GMV and ShopBack user base. Contributes almost nothing inside the 12-month window.
B23: Confidence legend: Low = no evidence, pure judgement | Medium = industry benchmark exists | Unknown = ShopBack has this number, I do not

Sheet Lens funnel
A1: Lens funnel - Singapore, month 12 run-rate
A2: Every cell below is a formula. Change the Assumptions tab and this recalculates.
A4: Step | B4: Driver | C4: Monthly volume | D4: Unit | E4: Assumption
A5: Singapore monthly active users | C5: =Assumptions!$C$5 | D5: users | E5: A-13
A6: Users who use Lens at least once this month | B6: =Assumptions!$C$7 | C6: =C5*Assumptions!$C$7 | D6: users | E6: A-2
A7: Lens submissions (links, screenshots, questions) | B7: =Assumptions!$C$8 | C7: =C6*Assumptions!$C$8 | D7: submissions | E7: A-3
A8: Resolved to a confident product match | B8: =Assumptions!$C$9 | C8: =C7*Assumptions!$C$9 | D8: matches | E8: A-4
A9: Tapped through to a merchant (tracked click-out) | B9: =Assumptions!$C$10 | C9: =C8*Assumptions!$C$10 | D9: click-outs | E9: A-6
A10: Orders placed | B10: =Assumptions!$C$11 | C10: =C9*Assumptions!$C$11 | D10: orders | E10: A-7
A11: Of which INCREMENTAL (would not have been tracked) | B11: =Assumptions!$C$12 | C11: =C10*Assumptions!$C$12 | D11: orders | E11: A-8
A12: Incremental GMV per month | B12: =Assumptions!$C$13 | C12: =C11*Assumptions!$C$13 | D12: SGD | E12: A-12
A14: ANNUALISED AT MONTH-12 RUN-RATE
A15: Incremental GMV from Lens orders | C15: =C12*12 | D15: SGD
A16: Additional GMV from retention lift (orders placed outside Lens) | B16: =Assumptions!$C$14 | C16: =C6*Assumptions!$C$14*Assumptions!$C$13*12 | D16: SGD | E16: A-11
A17: Total incremental GMV | C17: =C15+C16 | D17: SGD
A18: Net revenue to ShopBack from Lens | B18: =Assumptions!$C$15 | C18: =C17*Assumptions!$C$15 | D18: SGD | E18: P-2
A20: Annual resolution cost (all submissions, matched or not) | B20: =Assumptions!$C$19 | C20: =C7*12*Assumptions!$C$19 | D20: SGD | E20: A-10
A21: Fully loaded team cost | C21: =Assumptions!$C$20 | D21: SGD | E21: A-17
A24: Read this as: the arithmetic consequence of the assumptions, not a forecast. The Lens revenue line alone does not cover team cost in year one - that is expected and is why Smart Rates is in scope. See the next tab.

Sheet Smart Rates
A1: Smart Rates - platform fee on participating GMV
A2: Extra cashback is a merchant-funded pass-through. ShopBack's new line is a 71 bps fee for allocation and holdout measurement.
A4: Step | B4: Driver | C4: Value | D4: Unit | E4: Assumption
A5: SG annual tracked GMV (the whole book) | C5: =Assumptions!$C$16 | D5: SGD | E5: A-15
A6: GMV from merchants who activate Smart Rates | B6: =Assumptions!$C$17 | C6: =C5*Assumptions!$C$17 | D6: SGD | E6: A-9
A7: Platform fee on participating GMV | B7: =Assumptions!$C$18 | C7: =C6*Assumptions!$C$18 | D7: SGD | E7: A-16
A9: COMBINED 12-MONTH PICTURE (Singapore only)
A10: Net revenue - Lens | C10: ='Lens funnel'!$C$18 | D10: SGD
A11: Net revenue - Smart Rates | C11: =C7 | D11: SGD
A12: Total net revenue impact | C12: =C10+C11 | D12: SGD
A13: Less: resolution cost | C13: =-'Lens funnel'!$C$20 | D13: SGD
A14: Less: fully loaded team cost | C14: =-'Lens funnel'!$C$21 | D14: SGD
A15: Year-1 contribution (negative is expected - see note) | C15: =C12+C13+C14 | D15: SGD
A17: M12 EXIT RUN-RATE including MY + TW | B17: =Assumptions!$C$21 | C17: =C12*Assumptions!$C$21 | D17: SGD | E17: A-18
A19: Exit run-rate matters more than year-1 P&L. Year one is a ramp: the annualised figures above are what the business is earning by month 12, not what it books across the 12 months. MY and TW launch in M10-M12 and contribute almost nothing inside the window, but they set the exit run-rate. The honest framing to leadership is that year one buys the run-rate and year two collects it - and the model is built so you can check that claim rather than trust it.
A21: How Smart Rates is paid for
A22: Three claims cannot be true at once: rates only go up, merchant spend is unchanged, and ShopBack margin expands by cutting ACTIVE users. The last of those is not the design.
A23: The extra cashback NEW and LAPSED customers see is funded from an optional merchant acquisition budget, on top of the published base rate. ACTIVE customers keep the public rate. ShopBack does not fund the boost, and does not pay for it by reducing anyone. Merchant base affiliate spend is unchanged; total spend rises by the optional budget plus the fee.
A24: ShopBack's new revenue line is a 71 bps platform fee on GMV from participating merchants, charged for allocation and a holdout-verified incrementality report - the same shape as a managed-service fee. Extra cashback paid to shoppers is a pass-through of the merchant's boost budget and is not booked as ShopBack margin. Guardrail: a user NEVER sees a rate below the published base.

Sheet Scenarios
A1: Scenarios
A2: Four uncertain inputs varied. Incremental GMV and net revenue INCLUDE retention lift, matching the PRD and deck.
A4: Driver | B4: Conservative | C4: Base | D4: Aggressive | E4: Note
A5: Lens adoption (A-2) | B5: 0.1 | C5: 0.22 | D5: 0.35 | E5: Conservative assumes only prompted discovery works
A6: Match rate (A-4) | B6: 0.62 | C6: 0.78 | D6: 0.88 | E6: Conservative assumes catalogue gaps on long-tail SKUs
A7: Incrementality (A-8) | B7: 0.35 | C7: 0.55 | D7: 0.7 | E7: Conservative assumes heavy cannibalisation of existing tracked traffic
A8: Smart Rates GMV participation (A-9) | B8: 0.15 | C8: 0.35 | D8: 0.55 | E8: Conservative assumes only the pilot cohort renews
A10: Monthly orders via Lens | B10: =$B$5*Assumptions!$C$5*Assumptions!$C$8*$B$6*Assumptions!$C$10*Assumptions!$C$11 | C10: =$C$5*Assumptions!$C$5*Assumptions!$C$8*$C$6*Assumptions!$C$10*Assumptions!$C$11 | D10: =$D$5*Assumptions!$C$5*Assumptions!$C$8*$D$6*Assumptions!$C$10*Assumptions!$C$11
A11: Monthly incremental orders | B11: =$B$5*Assumptions!$C$5*Assumptions!$C$8*$B$6*Assumptions!$C$10*Assumptions!$C$11*$B$7 | C11: =$C$5*Assumptions!$C$5*Assumptions!$C$8*$C$6*Assumptions!$C$10*Assumptions!$C$11*$C$7 | D11: =$D$5*Assumptions!$C$5*Assumptions!$C$8*$D$6*Assumptions!$C$10*Assumptions!$C$11*$D$7
A12: Annualised incremental GMV (Lens + retention lift) | B12: =($B$5*Assumptions!$C$5*Assumptions!$C$8*$B$6*Assumptions!$C$10*Assumptions!$C$11*$B$7*Assumptions!$C$13)*12 + Assumptions!$C$5*$B$5*Assumptions!$C$14*Assumptions!$C$13*12 | C12: =($C$5*Assumptions!$C$5*Assumptions!$C$8*$C$6*Assumptions!$C$10*Assumptions!$C$11*$C$7*Assumptions!$C$13)*12 + Assumptions!$C$5*$C$5*Assumptions!$C$14*Assumptions!$C$13*12 | D12: =($D$5*Assumptions!$C$5*Assumptions!$C$8*$D$6*Assumptions!$C$10*Assumptions!$C$11*$D$7*Assumptions!$C$13)*12 + Assumptions!$C$5*$D$5*Assumptions!$C$14*Assumptions!$C$13*12
A13: Net revenue - Lens | B13: =($B$5*Assumptions!$C$5*Assumptions!$C$8*$B$6*Assumptions!$C$10*Assumptions!$C$11*$B$7*Assumptions!$C$13)*12 + Assumptions!$C$5*$B$5*Assumptions!$C$14*Assumptions!$C$13*12*Assumptions!$C$15 | C13: =($C$5*Assumptions!$C$5*Assumptions!$C$8*$C$6*Assumptions!$C$10*Assumptions!$C$11*$C$7*Assumptions!$C$13)*12 + Assumptions!$C$5*$C$5*Assumptions!$C$14*Assumptions!$C$13*12*Assumptions!$C$15 | D13: =($D$5*Assumptions!$C$5*Assumptions!$C$8*$D$6*Assumptions!$C$10*Assumptions!$C$11*$D$7*Assumptions!$C$13)*12 + Assumptions!$C$5*$D$5*Assumptions!$C$14*Assumptions!$C$13*12*Assumptions!$C$15
A14: Net revenue - Smart Rates platform fee | B14: =Assumptions!$C$16*$B$8*Assumptions!$C$18 | C14: =Assumptions!$C$16*$C$8*Assumptions!$C$18 | D14: =Assumptions!$C$16*$D$8*Assumptions!$C$18
A15: TOTAL net revenue impact | B15: =($B$5*Assumptions!$C$5*Assumptions!$C$8*$B$6*Assumptions!$C$10*Assumptions!$C$11*$B$7*Assumptions!$C$13)*12 + Assumptions!$C$5*$B$5*Assumptions!$C$14*Assumptions!$C$13*12*Assumptions!$C$15 + Assumptions!$C$16*$B$8*Assumptions!$C$18 | C15: =($C$5*Assumptions!$C$5*Assumptions!$C$8*$C$6*Assumptions!$C$10*Assumptions!$C$11*$C$7*Assumptions!$C$13)*12 + Assumptions!$C$5*$C$5*Assumptions!$C$14*Assumptions!$C$13*12*Assumptions!$C$15 + Assumptions!$C$16*$C$8*Assumptions!$C$18 | D15: =($D$5*Assumptions!$C$5*Assumptions!$C$8*$D$6*Assumptions!$C$10*Assumptions!$C$11*$D$7*Assumptions!$C$13)*12 + Assumptions!$C$5*$D$5*Assumptions!$C$14*Assumptions!$C$13*12*Assumptions!$C$15 + Assumptions!$C$16*$D$8*Assumptions!$C$18
A16: M12 exit run-rate incl. MY + TW | B16: =(($B$5*Assumptions!$C$5*Assumptions!$C$8*$B$6*Assumptions!$C$10*Assumptions!$C$11*$B$7*Assumptions!$C$13)*12 + Assumptions!$C$5*$B$5*Assumptions!$C$14*Assumptions!$C$13*12*Assumptions!$C$15 + Assumptions!$C$16*$B$8*Assumptions!$C$18)*Assumptions!$C$21 | C16: =(($C$5*Assumptions!$C$5*Assumptions!$C$8*$C$6*Assumptions!$C$10*Assumptions!$C$11*$C$7*Assumptions!$C$13)*12 + Assumptions!$C$5*$C$5*Assumptions!$C$14*Assumptions!$C$13*12*Assumptions!$C$15 + Assumptions!$C$16*$C$8*Assumptions!$C$18)*Assumptions!$C$21 | D16: =(($D$5*Assumptions!$C$5*Assumptions!$C$8*$D$6*Assumptions!$C$10*Assumptions!$C$11*$D$7*Assumptions!$C$13)*12 + Assumptions!$C$5*$D$5*Assumptions!$C$14*Assumptions!$C$13*12*Assumptions!$C$15 + Assumptions!$C$16*$D$8*Assumptions!$C$18)*Assumptions!$C$21
A18: The argument is the asymmetry, not the base case. Conservative still produces a S$0.50M Singapore run-rate and a S$1.6M three-market exit run-rate. That does not cover S$2.6M of team cost in year one. Fund it if A-1 and A-4 clear their Phase 0 gates; kill it in month one if they do not.

Sheet Metrics
A1: Metrics tree
A2: North star, inputs, guardrails and the counter-metric that keeps us honest.
A4: Tier | B4: Metric | C4: Definition | D4: M12 target | E4: Cadence / owner
A5: NORTH STAR | B5: Incremental tracked GMV per MAU | C5: Tracked GMV attributable to Lens, measured against a randomised holdout, divided by monthly actives. Chosen over raw usage (inflatable) and raw GMV (rewards cannibalisation). | D5: +S$1.57 /mo | E5: Monthly / PM
A6: Input | B6: Share-extension install rate | C6: Share of app users who have enabled the iOS/Android share target | D6: 45% | E6: Weekly / PM
A7: Input | B7: Lens MAU / total MAU | C7: Users submitting at least one item per month | D7: 22% | E7: Weekly / PM
A8: Input | B8: Submissions per Lens user | C8: Capture habit strength. Below 1.5 means novelty, not habit. | D8: 3.2 | E8: Weekly / PM
A9: Input | B9: Match rate by path | C9: Confident matches, split URL / image / text. Diagnoses catalogue gaps. | D9: 78% blended | E9: Weekly / Eng
A10: Input | B10: Time to first answer, p50 / p95 | C10: Capture tap to rendered price card | D10: 1.1s / 2.5s | E10: Daily / Eng
A11: Input | B11: Match to click-out | C11: Is the answer compelling enough to act on | D11: 46% | E11: Weekly / PM
A12: Input | B12: Click-out to order | C12: Benchmarked against current ShopBack click-out conversion | D12: 9.5% | E12: Weekly / PM
A13: Input | B13: Watchlist alert to return rate | C13: The frequency engine. Drives sessions between purchases. | D13: 28% | E13: Weekly / PM
A14: Business | B14: Incremental orders and GMV | C14: Read off the holdout, never off Lens-cohort behaviour alone | D14: 7.9k orders/mo | E14: Monthly / Finance
A15: Business | B15: Smart Rates budget under management | C15: Committed monthly merchant cashback budget across participating merchants | D15: S$0.6M/mo | E15: Monthly / BD
... A23: COUNTER | B23: Tracked orders per user, NON-Lens cohort | C23: If Lens creates value this stays flat while the Lens cohort rises. If it falls, Lens is redistributing, not creating - and we would rather find that ourselves than have Finance find it. | D23: Flat | E23: Monthly / PM
